MANIFEST.in
README.rst
requirements.txt
setup.cfg
setup.py
djmicrosip/__init__.py
djmicrosip/__init__.pyc
djmicrosip.egg-info/PKG-INFO
djmicrosip.egg-info/SOURCES.txt
djmicrosip.egg-info/dependency_links.txt
djmicrosip.egg-info/requires.txt
djmicrosip.egg-info/top_level.txt
djmicrosip/comun/__init__.py
djmicrosip/comun/__init__.pyc
djmicrosip/comun/articulos/__init__.py
djmicrosip/comun/articulos/__init__.pyc
djmicrosip/comun/articulos/admin.pyc
djmicrosip/comun/articulos/models.pyc
djmicrosip/comun/articulos/tests.pyc
djmicrosip/comun/articulos/views.pyc
djmicrosip/comun/articulos/migrations/__init__.py
djmicrosip/comun/articulos/migrations/__init__.pyc
djmicrosip/comun/clientes/__init__.py
djmicrosip/comun/clientes/__init__.pyc
djmicrosip/comun/clientes/admin.pyc
djmicrosip/comun/clientes/models.pyc
djmicrosip/comun/clientes/tests.pyc
djmicrosip/comun/clientes/views.pyc
djmicrosip/comun/clientes/migrations/__init__.py
djmicrosip/comun/clientes/migrations/__init__.pyc
djmicrosip/comun/direcciones/__init__.py
djmicrosip/comun/direcciones/__init__.pyc
djmicrosip/comun/direcciones/admin.pyc
djmicrosip/comun/direcciones/models.pyc
djmicrosip/comun/direcciones/tests.pyc
djmicrosip/comun/direcciones/views.pyc
djmicrosip/comun/direcciones/migrations/__init__.py
djmicrosip/comun/direcciones/migrations/__init__.pyc
djmicrosip/comun/general/__init__.py
djmicrosip/comun/general/__init__.pyc
djmicrosip/comun/general/admin.pyc
djmicrosip/comun/general/models.pyc
djmicrosip/comun/general/tests.pyc
djmicrosip/comun/general/views.pyc
djmicrosip/comun/general/migrations/__init__.py
djmicrosip/comun/general/migrations/__init__.pyc
djmicrosip/comun/impuestos/__init__.py
djmicrosip/comun/impuestos/__init__.pyc
djmicrosip/comun/impuestos/admin.pyc
djmicrosip/comun/impuestos/models.pyc
djmicrosip/comun/impuestos/tests.pyc
djmicrosip/comun/impuestos/views.pyc
djmicrosip/comun/impuestos/migrations/__init__.py
djmicrosip/comun/impuestos/migrations/__init__.pyc
djmicrosip/comun/listas/__init__.py
djmicrosip/comun/listas/__init__.pyc
djmicrosip/comun/listas/admin.pyc
djmicrosip/comun/listas/models.pyc
djmicrosip/comun/listas/tests.pyc
